deeplite/model_converter/converter.cpython-37m-x86_64-linux-gnu.so
deeplite/model_converter/formatter.cpython-37m-x86_64-linux-gnu.so
deeplite/model_converter/__init__.cpython-37m-x86_64-linux-gnu.so
deeplite/model_converter/pytorch_converter/_base.cpython-37m-x86_64-linux-gnu.so
deeplite/model_converter/pytorch_converter/pytorch_converter.cpython-37m-x86_64-linux-gnu.so
deeplite/model_converter/pytorch_converter/__init__.cpython-37m-x86_64-linux-gnu.so
deeplite/model_converter/tf_converter/tf_converter.cpython-37m-x86_64-linux-gnu.so
deeplite/model_converter/tf_converter/_base.cpython-37m-x86_64-linux-gnu.so
deeplite/model_converter/tf_converter/__init__.cpython-37m-x86_64-linux-gnu.so
examples/scripts/run_onnx_model.py
examples/scripts/run_tflite_model.py
examples/converters/pytorch2tflite_ssd300.py
examples/converters/pytorch2tflite_classification.py
deeplite_model_converter-1.2.4.dist-info/METADATA
deeplite_model_converter-1.2.4.dist-info/RECORD
deeplite_model_converter-1.2.4.dist-info/top_level.txt
deeplite_model_converter-1.2.4.dist-info/LICENSE
deeplite_model_converter-1.2.4.dist-info/WHEEL
