Metadata-Version: 2.1
Name: deeplite-model-converter
Version: 1.2.4
Summary: Converter of Deep Learning Model Formats
Home-page: https://github.com/Deeplite/deeplite-model-converterr
Author: Deeplite
Author-email: support@deeplite.ai
License: Apache 2.0
Keywords: converter deep_neural_network deep_learning torch onnx tf tflite
Platform: UNKNOWN
Classifier: Development Status :: 5 - Production/Stable
Classifier: Intended Audience :: Science/Research
Classifier: Intended Audience :: Developers
Classifier: Programming Language :: Python
Classifier: Programming Language :: Python :: 3.6
Classifier: Programming Language :: Python :: 3.7
Classifier: Programming Language :: Python :: 3.8
Classifier: Programming Language :: Python :: Implementation :: CPython
Classifier: Topic :: Scientific/Engineering :: Artificial Intelligence
Classifier: Topic :: Software Development :: Libraries :: Python Modules
Classifier: Operating System :: POSIX :: Linux
Classifier: Natural Language :: English
Classifier: License :: OSI Approved :: Apache Software License
Classifier: Environment :: Console
Requires-Dist: deeplite-profiler (>=1.2.1)
Requires-Dist: onnx (<1.12.0)
Requires-Dist: onnxruntime (==1.10.0)
Requires-Dist: onnx-simplifier (==0.3.9)
Requires-Dist: setuptools (<65.6.0)
Requires-Dist: onnxoptimizer (==0.2.7) ; python_version == "3.6"
Provides-Extra: all
Requires-Dist: torch (<=1.8.1,>=1.4) ; extra == 'all'
Requires-Dist: tensorflow (==2.5) ; extra == 'all'
Requires-Dist: onnx-tf (==1.8.0) ; extra == 'all'
Provides-Extra: tf
Requires-Dist: tensorflow (==2.5) ; extra == 'tf'
Requires-Dist: onnx-tf (==1.8.0) ; extra == 'tf'
Provides-Extra: torch
Requires-Dist: torch (<=1.8.1,>=1.4) ; extra == 'torch'
